TESLA/ConnectedComponents.py
TESLA/TESLA.py
TESLA/TLS_detection.py
TESLA/__init__.py
TESLA/annotation.py
TESLA/calculate_dis.py
TESLA/contour_util.py
TESLA/imputation.py
TESLA/models.py
TESLA/tumor_edge_core.py
TESLA/util.py
TESLAforST-1.2.2.dist-info/DESCRIPTION.rst
TESLAforST-1.2.2.dist-info/METADATA
TESLAforST-1.2.2.dist-info/RECORD
TESLAforST-1.2.2.dist-info/WHEEL
TESLAforST-1.2.2.dist-info/metadata.json
TESLAforST-1.2.2.dist-info/top_level.txt
