Metadata-Version: 2.0
Name: TESLAforST
Version: 1.2.2
Summary: TESLA: Deciphering tumor ecosystems at super-resolution from spatial transcriptomics
Home-page: https://github.com/jianhuupenn/TESLA
Author: Jian Hu
Author-email: jianhu@pennmedicine.upenn.edu
License: UNKNOWN
Platform: UNKNOWN
Classifier: Programming Language :: Python :: 3
Classifier: License :: OSI Approved :: MIT License
Classifier: Operating System :: OS Independent
Requires-Python: >=3.6
Requires-Dist: anndata
Requires-Dist: numba
Requires-Dist: numpy
Requires-Dist: pandas
Requires-Dist: scanpy
Requires-Dist: scipy
Requires-Dist: sklearn
Requires-Dist: torch
